lc_local_samueldsr99/__init__.py
lc_local_samueldsr99/lc_local.py
lc_local_samueldsr99/services/template_service/__init__.py
lc_local_samueldsr99/services/template_service/template_service.py
lc_local_samueldsr99/services/template_service/queries/question_editor_data.py
lc_local_samueldsr99-0.0.1.dist-info/LICENSE.md
lc_local_samueldsr99-0.0.1.dist-info/METADATA
lc_local_samueldsr99-0.0.1.dist-info/WHEEL
lc_local_samueldsr99-0.0.1.dist-info/top_level.txt
lc_local_samueldsr99-0.0.1.dist-info/RECORD
