Metadata-Version: 2.1
Name: lc_local_samueldsr99
Version: 0.0.1
Summary: Leetcode local environment
Author-email: Samuel David <samueldsr8@gmail.com>
Project-URL: Homepage, https://github.com/samueldsr99/leetcode-local
Project-URL: Bug Tracker, https://github.com/samueldsr99/leetcode-local/issues
Classifier: Programming Language :: Python :: 3
Classifier: License :: OSI Approved :: MIT License
Classifier: Operating System :: OS Independent
Requires-Python: >=3.7
License-File: LICENSE.md
